jun_tools/__init__.py
jun_tools/jun_mtd.py
YjmTools-0.0.1.dist-info/LICENSE
YjmTools-0.0.1.dist-info/METADATA
YjmTools-0.0.1.dist-info/WHEEL
YjmTools-0.0.1.dist-info/top_level.txt
YjmTools-0.0.1.dist-info/RECORD
