Metadata-Version: 2.1
Name: YjmTools
Version: 0.0.1
Summary: jun's tools
Home-page: https://github.com/yajumo93/JunTools.git
Author: Junmo Yang
Author-email: yajumo93@gmail.com
License: MIT
Platform: UNKNOWN
Classifier: Programming Language :: Python :: 3
Classifier: License :: OSI Approved :: MIT License
Classifier: Operating System :: OS Independent
License-File: LICENSE
